MANIFEST.in
README.rst
setup.cfg
setup.py
mutalk/__init__.py
mutalk/net.py
mutalk.egg-info/PKG-INFO
mutalk.egg-info/SOURCES.txt
mutalk.egg-info/dependency_links.txt
mutalk.egg-info/top_level.txt
test/__init__.py
test/test_integration.py