Metadata-Version: 1.1
Name: mutalk
Version: 1.0.0
Summary: Mutlicast messaging library
Home-page: https://github.com/mutalk/python
Author: Baryshnikov Alexander
Author-email: dev@baryshnikov.net
License: MIT
Keywords: mutalk multicast messaging
Platform: UNKNOWN
Classifier: Development Status :: 5 - Production/Stable
Classifier: Intended Audience :: Developers
Classifier: Topic :: System :: Networking
Classifier: License :: OSI Approved :: MIT License
Classifier: Programming Language :: Python :: 3.5
